Workbook

Sheet Cover
C5: FAMILY BANK LIMITED
C7: Five-Year Bank Financial Model | 2026 – 2030
D10: Currency: | G10: KES – Millions
D11: Projection Period: | G11: 2026 to 2030 (5 Years)
D12: Scenarios: | G12: Base Case | Best Case | Worst Case
D13: Prepared By: | G13: Family Bank Limited — Management
D14: Classification: | G14: This document is strictly confidential
C17: Model Contents
D19: • Summary
D20: • Assumptions
D21: • Scenarios
D22: • Model (Loan Book, IFRS 9, Statements, Capital, Liquidity)
D23: • Output (DDM, Residual Income, P/B-ROE)
D24: • Sources (external market-data references)

Sheet Summary
C1: Family Bank Limited | O1: =HYPERLINK("#'Scenarios'!D5","Currently running: "&UPPER(CHOOSE('Scenarios'!$D$5,"Base","Best","Worst"))&" CASE")
C3: Summary Financial Outputs — Three Scenarios
B5: BASE CASE — Financial Summary
K6: 2026P | L6: 2027P | M6: 2028P | N6: 2029P | O6: 2030P
C8: Total Income (NII + Non-Interest) | F8: (KES MM) | K8: 21779.052 | L8: 23349.276 | M8: 25023.828 | N8: 26805.88 | O8: 28697.672
C9: Net Interest Income | F9: (KES MM) | K9: 17293.617 | L9: 18154.577 | M9: 19007.063 | N9: 19836.214 | O9: 20623.339
C10: Net Profit After Tax | F10: (KES MM) | K10: 6771.0102 | L10: 7189.9095 | M10: 7475.9084 | N10: 7786.3899 | O10: 8111.198
C11: Total Capital Ratio | K11: 0.19632063 | L11: 0.19818089 | M11: 0.19828686 | N11: 0.19695911 | O11: 0.1944443
C12: NPL Ratio | K12: 0.10770863 | L12: 0.095274601 | M12: 0.08669026 | N12: 0.080719822 | O12: 0.076536949
B14: BEST CASE — Financial Summary
K15: 2026P | L15: 2027P | M15: 2028P | N15: 2029P | O15: 2030P
C17: Total Income (NII + Non-Interest) | F17: (KES MM) | K17: 22154.378 | L17: 24196.467 | M17: 26458.271 | N17: 28965.116 | O17: 31745.246
C18: Net Interest Income | F18: (KES MM) | K18: 17668.943 | L18: 19001.768 | M18: 20441.506 | N18: 21995.45 | O18: 23670.912
C19: Net Profit After Tax | F19: (KES MM) | K19: 7051.2389 | L19: 7858.7878 | M19: 8649.261 | N19: 9565.3722 | O19: 10618
C20: Total Capital Ratio | K20: 0.19327577 | L20: 0.19301477 | M20: 0.19194813 | N20: 0.19030667 | O20: 0.18825922
C21: NPL Ratio | K21: 0.10553776 | L21: 0.091467234 | M21: 0.081651592 | N21: 0.074757482 | O21: 0.069884229
B23: WORST CASE — Financial Summary
K24: 2026P | L24: 2027P | M24: 2028P | N24: 2029P | O24: 2030P
C26: Total Income (NII + Non-Interest) | F26: (KES MM) | K26: 21216.062 | L26: 22111.401 | M26: 22982.159 | N26: 23812.161 | O26: 24581.651
C27: Net Interest Income | F27: (KES MM) | K27: 16730.627 | L27: 16916.701 | M27: 16965.394 | N27: 16842.494 | O27: 16507.317
C28: Net Profit After Tax | F28: (KES MM) | K28: 6351.0065 | L28: 6218.4552 | M28: 5797.9425 | N28: 5292.4565 | O28: 4669.8122
C29: Total Capital Ratio | K29: 0.20113416 | L29: 0.2065442 | M29: 0.20868837 | N29: 0.20788453 | O29: 0.20436682
C30: NPL Ratio | K30: 0.11113771 | L30: 0.10144532 | M30: 0.095060291 | N30: 0.090855261 | O30: 0.088088071
C32: IMPLIED VALUE PER SHARE BY SCENARIO (KES per share)
H33: Base | I33: Best | J33: Worst
C34: Dividend Discount Model (DDM) | H34: 7.7238148 | I34: 9.5770641 | J34: 5.1600606
C35: Residual Income / Excess Return | H35: 11.987741 | I35: 17.825587 | J35: 3.983978
C36: P/B-ROE Regression (relative) | H36: 33.687922 | I36: 41.902741 | J36: 22.844509
C37: Blended Valuation | H37: 14.195814 | I37: 18.516756 | J37: 8.3441255
C39: RATIO DISCLOSURES — BASE CASE (live-linked to Model sheet)
H40: 2023A | I40: 2024A | J40: 2025A | K40: 2026P | L40: 2027P | M40: 2028P | N40: 2029P | O40: 2030P
C42: Profitability (CAMELS: Earnings)
C43: Return on Equity (ROE) | I43: =IFERROR('Model'!I140/(('Model'!H206+'Model'!I206)/2),0) | J43: =IFERROR('Model'!J140/(('Model'!I206+'Model'!J206)/2),0) | K43: =IFERROR('Model'!K140/(('Model'!J206+'Model'!K206)/2),0) | L43: =IFERROR('Model'!L140/(('Model'!K206+'Model'!L206)/2),0) | M43: =IFERROR('Model'!M140/(('Model'!L206+'Model'!M206)/2),0) | N43: =IFERROR('Model'!N140/(('Model'!M206+'Model'!N206)/2),0) | O43: =IFERROR('Model'!O140/(('Model'!N206+'Model'!O206)/2),0)
C44: Net Interest Margin (proxy: NII / Total Deposits) | H44: =IFERROR('Model'!H124/'Model'!H118,0) | I44: =IFERROR('Model'!I124/'Model'!I118,0) | J44: =IFERROR('Model'!J124/'Model'!J118,0) | K44: =IFERROR('Model'!K124/'Model'!K118,0) | L44: =IFERROR('Model'!L124/'Model'!L118,0) | M44: =IFERROR('Model'!M124/'Model'!M118,0) | N44: =IFERROR('Model'!N124/'Model'!N118,0) | O44: =IFERROR('Model'!O124/'Model'!O118,0)
C45: Cost-to-Income Ratio | H45: =IFERROR('Model'!H136/('Model'!H124+'Model'!H129),0) | I45: =IFERROR('Model'!I136/('Model'!I124+'Model'!I129),0) | J45: =IFERROR('Model'!J136/('Model'!J124+'Model'!J129),0) | K45: =IFERROR('Model'!K136/('Model'!K124+'Model'!K129),0) | L45: =IFERROR('Model'!L136/('Model'!L124+'Model'!L129),0) | M45: =IFERROR('Model'!M136/('Model'!M124+'Model'!M129),0) | N45: =IFERROR('Model'!N136/('Model'!N124+'Model'!N129),0) | O45: =IFERROR('Model'!O136/('Model'!O124+'Model'!O129),0)
C47: Capital Adequacy (CAMELS: Capital)
C48: Core Capital / RWA | H48: ='Model'!H233 | I48: ='Model'!I233 | J48: ='Model'!J233 | K48: ='Model'!K233 | L48: ='Model'!L233 | M48: ='Model'!M233 | N48: ='Model'!N233 | O48: ='Model'!O233
C49: Total Capital / RWA | H49: ='Model'!H234 | I49: ='Model'!I234 | J49: ='Model'!J234 | K49: ='Model'!K234 | L49: ='Model'!L234 | M49: ='Model'!M234 | N49: ='Model'!N234 | O49: ='Model'!O234
C51: Liquidity (CAMELS: Liquidity)
C52: Liquidity Ratio | H52: ='Model'!H239 | I52: ='Model'!I239 | J52: ='Model'!J239 | K52: ='Model'!K239 | L52: ='Model'!L239 | M52: ='Model'!M239 | N52: ='Model'!N239 | O52: ='Model'!O239
C54: Cash Flow Ratios
C55: Operating Cash Flow / PAT | H55: =IFERROR('Model'!H171/'Model'!H140,0) | I55: =IFERROR('Model'!I171/'Model'!I140,0) | J55: =IFERROR('Model'!J171/'Model'!J140,0) | K55: =IFERROR('Model'!K171/'Model'!K140,0) | L55: =IFERROR('Model'!L171/'Model'!L140,0) | M55: =IFERROR('Model'!M171/'Model'!M140,0) | N55: =IFERROR('Model'!N171/'Model'!N140,0) | O55: =IFERROR('Model'!O171/'Model'!O140,0)
C56: Operating Cash Flow / Total Deposits | H56: =IFERROR('Model'!H171/'Model'!H118,0) | I56: =IFERROR('Model'!I171/'Model'!I118,0) | J56: =IFERROR('Model'!J171/'Model'!J118,0) | K56: =IFERROR('Model'!K171/'Model'!K118,0) | L56: =IFERROR('Model'!L171/'Model'!L118,0) | M56: =IFERROR('Model'!M171/'Model'!M118,0) | N56: =IFERROR('Model'!N171/'Model'!N118,0) | O56: =IFERROR('Model'!O171/'Model'!O118,0)
C58: KEY NET INCOME SENSITIVITIES (Base Case, one factor at a time)
J59: Average-PAT % impact of shocking one driver in isolation, others held at Base — not the combined Best/Worst scenarios above. See BLUEPRINT.md / research_output.md for methodology, shock sizes, and which candidate factors were tested and excluded for not moving PAT by more than 10%.
C60: Factor | G60: Category | J60: Downside | L60: Upside
C61: Loan/balance-sheet growth | G61: Macro — credit demand cycle — Worst 0.70x / Best 1.20x growth multiplier | J61: -0.19546693 | L61: 0.14029921
C62: Asset yield (lending rate) | G62: Bank-specific — rate cycle / repricing — +/-100bp parallel shift on loan yields | J62: -0.14975092 | L62: 0.14975092
C63: Cost of funds (deposit pricing) | G63: Macro — policy rate transmission — +/-100bp parallel shift on deposit cost | J63: -0.22683005 | L63: 0.22683005

Sheet Assumptions
C1: Family Bank Limited | O1: =HYPERLINK("#'Scenarios'!D5","Currently running: "&UPPER(CHOOSE('Scenarios'!$D$5,"Base","Best","Worst"))&" CASE")
C3: Inputs and Assumptions
C5: Data Provenance Legend
C6: ■ | D6: Disclosed fact (company filing)
C7: ■ | D7: Internal formula
C8: ■ | D8: Cross-sheet reference
C9: ■ | D9: Modeled proxy / benchmark / macro forecast — not directly disclosed
C11: GENERAL
C12: First forecast year | H12: 2026
C13: Tax rate | H13: 0.3
C14: Dividend payout ratio | H14: 0.25
C16: SCENARIO CONTROL
C17: Growth multiplier — Best | H17: 1.2 | J17: Switch lives on the Scenarios sheet ($D$5) — every row below tagged '(ACTIVE)' follows it live.
C18: Growth multiplier — Worst | H18: 0.7
C19: Loss-rate multiplier — Best | H19: 0.8
C20: Loss-rate multiplier — Worst | H20: 1.4
C21: Opex-escalation multiplier — Best | H21: 0.9
C22: Opex-escalation multiplier — Worst | H22: 1.15
C24: LOAN BOOK — BY PRODUCT (FY2025 opening; growth/rates scenario-switched)
H26: Term Loans | I26: Mortgage | J26: Overdraft & Credit Cards
C27: Opening gross — Stage 1 | H27: 74732.268 | I27: 12946.847 | J27: 1506.935
C28: Opening gross — Stage 2 | H28: 8355.106 | I28: 1580.111 | J28: 461.631
C29: Opening gross — Stage 3 | H29: 12303.29 | I29: 1395.34 | J29: 638.333
C30: Loss rate — Stage 1 (12m)
H32: =CHOOSE('Scenarios'!$D$5,H33,H34,H35) | I32: =CHOOSE('Scenarios'!$D$5,I33,I34,I35) | J32: =CHOOSE('Scenarios'!$D$5,J33,J34,J35)
C33: Base | H33: 0.01078 | I33: 0.001042 | J33: 0.003962
C34: Best | H34: =H33*Assumptions!$H$19 | I34: =I33*Assumptions!$H$19 | J34: =J33*Assumptions!$H$19
C35: Worst | H35: =H33*Assumptions!$H$20 | I35: =I33*Assumptions!$H$20 | J35: =J33*Assumptions!$H$20
C36: Loss rate — Stage 2 (lifetime)
H38: =CHOOSE('Scenarios'!$D$5,H39,H40,H41) | I38: =CHOOSE('Scenarios'!$D$5,I39,I40,I41) | J38: =CHOOSE('Scenarios'!$D$5,J39,J40,J41)
C39: Base | H39: 0.08044 | I39: 0.02806 | J39: 0.05966
C40: Best | H40: =H39*Assumptions!$H$19 | I40: =I39*Assumptions!$H$19 | J40: =J39*Assumptions!$H$19
C41: Worst | H41: =H39*Assumptions!$H$20 | I41: =I39*Assumptions!$H$20 | J41: =J39*Assumptions!$H$20
C42: Loss rate — Stage 3 (lifetime)
H44: =CHOOSE('Scenarios'!$D$5,H45,H46,H47) | I44: =CHOOSE('Scenarios'!$D$5,I45,I46,I47) | J44: =CHOOSE('Scenarios'!$D$5,J45,J46,J47)
C45: Base | H45: 0.48704 | I45: 0.14522 | J45: 0.40265
C46: Best | H46: =H45*Assumptions!$H$19 | I46: =I45*Assumptions!$H$19 | J46: =J45*Assumptions!$H$19
C47: Worst | H47: =H45*Assumptions!$H$20 | I47: =I45*Assumptions!$H$20 | J47: =J45*Assumptions!$H$20
C48: Gross loan growth p.a.
H50: =CHOOSE('Scenarios'!$D$5,H51,H52,H53) | I50: =CHOOSE('Scenarios'!$D$5,I51,I52,I53) | J50: =CHOOSE('Scenarios'!$D$5,J51,J52,J53)
C51: Base | H51: 0.12 | I51: 0.08 | J51: 0.13
C52: Best | H52: =H51*Assumptions!$H$17 | I52: =I51*Assumptions!$H$17 | J52: =J51*Assumptions!$H$17
C53: Worst | H53: =H51*Assumptions!$H$18 | I53: =I51*Assumptions!$H$18 | J53: =J51*Assumptions!$H$18
C54: Yield on loans | H54: 0.145 | I54: 0.125 | J54: 0.17
C55: SICR rate (Stage 1→2) | H55: 0.05 | I55: 0.04 | J55: 0.06
C56: Cure rate (Stage 2→1) | H56: 0.1 | I56: 0.1 | J56: 0.1
C57: Default rate (Stage 2→3) | H57: 0.15 | I57: 0.1 | J57: 0.18
C58: Cure rate (Stage 3→2) | H58: 0.05 | I58: 0.08 | J58: 0.05
C59: Write-off rate (of Stage 3) | H59: 0.1 | I59: 0.05 | J59: 0.15
C60: Risk weight (RWA) | H60: 1 | I60: 0.5 | J60: 1
C62: Off-Balance-Sheet Exposure
C63: Opening balance | H63: 3094.008
C64: Growth p.a. | H64: 0.1
C65: Credit conversion factor | H65: 0.2
C66: Risk weight | H66: 1
C68: FORWARD-LOOKING MACRO OVERLAY (IFRS 9)
C69: Weight — Base | H69: 0.6
C70: Weight — Upside | H70: 0.2
C71: Weight — Downside | H71: 0.2
C72: Multiplier — Base | H72: 1
C73: Multiplier — Upside | H73: 0.85
C74: Multiplier — Downside | H74: 1.3
C75: Blended macro multiplier (probability-weighted) | H75: =H69*H72+H70*H73+H71*H74
C77: DEPOSITS / FUNDING (allocation modeled — only the aggregate is disclosed)
H79: Demand / Current | I79: Savings | J79: Term / Fixed Deposits | K79: Wholesale / Interbank
C80: Opening balance | H80: 45731.2 | I80: 38109.34 | J80: 53353.07 | K80: 15243.73
C81: Growth p.a.
H83: =CHOOSE('Scenarios'!$D$5,H84,H85,H86) | I83: =CHOOSE('Scenarios'!$D$5,I84,I85,I86) | J83: =CHOOSE('Scenarios'!$D$5,J84,J85,J86) | K83: =CHOOSE('Scenarios'!$D$5,K84,K85,K86)
C84: Base | H84: 0.16 | I84: 0.15 | J84: 0.17 | K84: 0.13
C85: Best | H85: =H84*Assumptions!$H$17 | I85: =I84*Assumptions!$H$17 | J85: =J84*Assumptions!$H$17 | K85: =K84*Assumptions!$H$17
C86: Worst | H86: =H84*Assumptions!$H$18 | I86: =I84*Assumptions!$H$18 | J86: =J84*Assumptions!$H$18 | K86: =K84*Assumptions!$H$18
C87: Cost of funds | H87: 0.02 | I87: 0.04 | J87: 0.1 | K87: 0.11
C89: INVESTMENT SECURITIES
C90: Opening balance | H90: 74014.473
C91: Growth p.a. | H91: 0.05
C92: Yield | H92: 0.13
C94: NON-INTEREST INCOME
C95: Fee/commission income (% of deposits) | H95: 0.02541
C97: OPERATING EXPENSES
C98: Staff Costs — Year 1 | H98: 6438.2
C99: Staff Costs — escalation p.a.
H101: =CHOOSE('Scenarios'!$D$5,H102,H103,H104)
C102: Base | H102: 0.09
C103: Best | H103: =H102*Assumptions!$H$21
C104: Worst | H104: =H102*Assumptions!$H$22
C105: Premises & Branch Network — Year 1 | H105: 1639.7
C106: Premises & Branch Network — escalation p.a.
H108: =CHOOSE('Scenarios'!$D$5,H109,H110,H111)
C109: Base | H109: 0.06
C110: Best | H110: =H109*Assumptions!$H$21
C111: Worst | H111: =H109*Assumptions!$H$22
C112: Technology & Digital — Year 1 | H112: 1392.5
C113: Technology & Digital — escalation p.a.
H115: =CHOOSE('Scenarios'!$D$5,H116,H117,H118)
C116: Base | H116: 0.1
C117: Best | H117: =H116*Assumptions!$H$21
C118: Worst | H118: =H116*Assumptions!$H$22
C119: Other Operating Expenses — Year 1 | H119: 2406.9
C120: Other Operating Expenses — escalation p.a.
H122: =CHOOSE('Scenarios'!$D$5,H123,H124,H125)
...

Sheet Scenarios
C1: Family Bank Limited | O1: =HYPERLINK("#'Scenarios'!D5","Currently running: "&UPPER(CHOOSE('Scenarios'!$D$5,"Base","Best","Worst"))&" CASE")
C3: Scenario Comparison — Key Drivers
C5: SCENARIO SWITCH (1=Base, 2=Best, 3=Worst): | D5: 1 | G5: =UPPER(CHOOSE($D$5,"Base","Best","Worst"))&" CASE IS CURRENTLY LIVE ON THE MODEL SHEET"
C7: Modeled loan growth / IFRS 9 loss rates / opex escalation as calibrated per case (Best: growth x1.2, loss rates x0.8, opex x0.9 — Worst: growth x0.7, loss rates x1.4, opex x1.15)
B9: Total Income (KES MM) | K9: 2026P | L9: 2027P | M9: 2028P | N9: 2029P | O9: 2030P
K11: =CHOOSE('Scenarios'!$D$5,K12,K13,K14) | L11: =CHOOSE('Scenarios'!$D$5,L12,L13,L14) | M11: =CHOOSE('Scenarios'!$D$5,M12,M13,M14) | N11: =CHOOSE('Scenarios'!$D$5,N12,N13,N14) | O11: =CHOOSE('Scenarios'!$D$5,O12,O13,O14)
C12: Base | F12: (KES MM) | K12: 21779.052 | L12: 23349.276 | M12: 25023.828 | N12: 26805.88 | O12: 28697.672
C13: Best | F13: (KES MM) | K13: 22154.378 | L13: 24196.467 | M13: 26458.271 | N13: 28965.116 | O13: 31745.246
C14: Worst | F14: (KES MM) | K14: 21216.062 | L14: 22111.401 | M14: 22982.159 | N14: 23812.161 | O14: 24581.651
B16: Net Interest Income (KES MM) | K16: 2026P | L16: 2027P | M16: 2028P | N16: 2029P | O16: 2030P
K18: =CHOOSE('Scenarios'!$D$5,K19,K20,K21) | L18: =CHOOSE('Scenarios'!$D$5,L19,L20,L21) | M18: =CHOOSE('Scenarios'!$D$5,M19,M20,M21) | N18: =CHOOSE('Scenarios'!$D$5,N19,N20,N21) | O18: =CHOOSE('Scenarios'!$D$5,O19,O20,O21)
C19: Base | F19: (KES MM) | K19: 17293.617 | L19: 18154.577 | M19: 19007.063 | N19: 19836.214 | O19: 20623.339
C20: Best | F20: (KES MM) | K20: 17668.943 | L20: 19001.768 | M20: 20441.506 | N20: 21995.45 | O20: 23670.912
C21: Worst | F21: (KES MM) | K21: 16730.627 | L21: 16916.701 | M21: 16965.394 | N21: 16842.494 | O21: 16507.317
B23: Net Profit After Tax (KES MM) | K23: 2026P | L23: 2027P | M23: 2028P | N23: 2029P | O23: 2030P
K25: =CHOOSE('Scenarios'!$D$5,K26,K27,K28) | L25: =CHOOSE('Scenarios'!$D$5,L26,L27,L28) | M25: =CHOOSE('Scenarios'!$D$5,M26,M27,M28) | N25: =CHOOSE('Scenarios'!$D$5,N26,N27,N28) | O25: =CHOOSE('Scenarios'!$D$5,O26,O27,O28)
C26: Base | F26: (KES MM) | K26: 6771.0102 | L26: 7189.9095 | M26: 7475.9084 | N26: 7786.3899 | O26: 8111.198
C27: Best | F27: (KES MM) | K27: 7051.2389 | L27: 7858.7878 | M27: 8649.261 | N27: 9565.3722 | O27: 10618
C28: Worst | F28: (KES MM) | K28: 6351.0065 | L28: 6218.4552 | M28: 5797.9425 | N28: 5292.4565 | O28: 4669.8122
B30: NPL Ratio | K30: 2026P | L30: 2027P | M30: 2028P | N30: 2029P | O30: 2030P
K32: =CHOOSE('Scenarios'!$D$5,K33,K34,K35) | L32: =CHOOSE('Scenarios'!$D$5,L33,L34,L35) | M32: =CHOOSE('Scenarios'!$D$5,M33,M34,M35) | N32: =CHOOSE('Scenarios'!$D$5,N33,N34,N35) | O32: =CHOOSE('Scenarios'!$D$5,O33,O34,O35)
C33: Base | K33: 0.10770863 | L33: 0.095274601 | M33: 0.08669026 | N33: 0.080719822 | O33: 0.076536949
C34: Best | K34: 0.10553776 | L34: 0.091467234 | M34: 0.081651592 | N34: 0.074757482 | O34: 0.069884229
C35: Worst | K35: 0.11113771 | L35: 0.10144532 | M35: 0.095060291 | N35: 0.090855261 | O35: 0.088088071
B37: Total Capital Ratio | K37: 2026P | L37: 2027P | M37: 2028P | N37: 2029P | O37: 2030P
K39: =CHOOSE('Scenarios'!$D$5,K40,K41,K42) | L39: =CHOOSE('Scenarios'!$D$5,L40,L41,L42) | M39: =CHOOSE('Scenarios'!$D$5,M40,M41,M42) | N39: =CHOOSE('Scenarios'!$D$5,N40,N41,N42) | O39: =CHOOSE('Scenarios'!$D$5,O40,O41,O42)
C40: Base | K40: 0.19632063 | L40: 0.19818089 | M40: 0.19828686 | N40: 0.19695911 | O40: 0.1944443
C41: Best | K41: 0.19327577 | L41: 0.19301477 | M41: 0.19194813 | N41: 0.19030667 | O41: 0.18825922
C42: Worst | K42: 0.20113416 | L42: 0.2065442 | M42: 0.20868837 | N42: 0.20788453 | O42: 0.20436682
B44: Liquidity Ratio | K44: 2026P | L44: 2027P | M44: 2028P | N44: 2029P | O44: 2030P
K46: =CHOOSE('Scenarios'!$D$5,K47,K48,K49) | L46: =CHOOSE('Scenarios'!$D$5,L47,L48,L49) | M46: =CHOOSE('Scenarios'!$D$5,M47,M48,M49) | N46: =CHOOSE('Scenarios'!$D$5,N47,N48,N49) | O46: =CHOOSE('Scenarios'!$D$5,O47,O48,O49)
C47: Base | K47: 0.53719925 | L47: 0.55702776 | M47: 0.57483198 | N47: 0.59081661 | O47: 0.60519676
C48: Best | K48: 0.51388357 | L48: 0.5229328 | M48: 0.53141598 | N48: 0.53935591 | O48: 0.54679968
C49: Worst | K49: 0.57680612 | L49: 0.61108766 | M49: 0.64039141 | N49: 0.66532983 | O49: 0.68649485
B51: Return on Assets (avg) | K51: 2026P | L51: 2027P | M51: 2028P | N51: 2029P | O51: 2030P
K53: =CHOOSE('Scenarios'!$D$5,K54,K55,K56) | L53: =CHOOSE('Scenarios'!$D$5,L54,L55,L56) | M53: =CHOOSE('Scenarios'!$D$5,M54,M55,M56) | N53: =CHOOSE('Scenarios'!$D$5,N54,N55,N56) | O53: =CHOOSE('Scenarios'!$D$5,O54,O55,O56)
C54: Base | K54: 0.032207379 | L54: 0.030567003 | M54: 0.02755566 | N54: 0.024918369 | O54: 0.022560422
C55: Best | K55: 0.033393685 | L55: 0.033345302 | M55: 0.031745773 | N55: 0.030391842 | O55: 0.029218627
C56: Worst | K56: 0.030469541 | L56: 0.026513556 | M56: 0.021503387 | N56: 0.017114475 | O56: 0.013188984
B58: Return on Equity (avg) | K58: 2026P | L58: 2027P | M58: 2028P | N58: 2029P | O58: 2030P
K60: =CHOOSE('Scenarios'!$D$5,K61,K62,K63) | L60: =CHOOSE('Scenarios'!$D$5,L61,L62,L63) | M60: =CHOOSE('Scenarios'!$D$5,M61,M62,M63) | N60: =CHOOSE('Scenarios'!$D$5,N61,N62,N63) | O60: =CHOOSE('Scenarios'!$D$5,O61,O62,O63)
C61: Base | K61: 0.19543051 | L61: 0.18027964 | M61: 0.16473411 | N61: 0.15236055 | O61: 0.14213559
C62: Best | K62: 0.20290328 | L62: 0.19479936 | M62: 0.18587169 | N62: 0.17924769 | O62: 0.17425767
C63: Worst | K63: 0.18414513 | L63: 0.15862319 | M63: 0.13264921 | N63: 0.11056417 | O63: 0.09049395

Sheet Model
C1: Family Bank Limited | O1: =HYPERLINK("#'Scenarios'!D5","Currently running: "&UPPER(CHOOSE('Scenarios'!$D$5,"Base","Best","Worst"))&" CASE")
C2: Model — Scenario-Switched (fully formula-linked)
C4: MASTER CHECK
C5: Balance Sheet Check (Assets = Liab + Equity) | H5: =IF(ABS(H208)<0.01,"OK","ERROR") | I5: =IF(ABS(I208)<0.01,"OK","ERROR") | J5: =IF(ABS(J208)<0.01,"OK","ERROR") | K5: =IF(ABS(K208)<0.01,"OK","ERROR") | L5: =IF(ABS(L208)<0.01,"OK","ERROR") | M5: =IF(ABS(M208)<0.01,"OK","ERROR") | N5: =IF(ABS(N208)<0.01,"OK","ERROR") | O5: =IF(ABS(O208)<0.01,"OK","ERROR")
C6: Capital Adequacy Check (Total Capital ≥ CBK minimum) | H6: =IF(H234>=Assumptions!$H$131,"OK","ERROR") | I6: =IF(I234>=Assumptions!$H$131,"OK","ERROR") | J6: =IF(J234>=Assumptions!$H$131,"OK","ERROR") | K6: =IF(K234>=Assumptions!$H$131,"OK","ERROR") | L6: =IF(L234>=Assumptions!$H$131,"OK","ERROR") | M6: =IF(M234>=Assumptions!$H$131,"OK","ERROR") | N6: =IF(N234>=Assumptions!$H$131,"OK","ERROR") | O6: =IF(O234>=Assumptions!$H$131,"OK","ERROR")
C7: Liquidity Check (≥ CBK statutory minimum) | H7: =IF(H239>=Assumptions!$H$146,"OK","ERROR") | I7: =IF(I239>=Assumptions!$H$146,"OK","ERROR") | J7: =IF(J239>=Assumptions!$H$146,"OK","ERROR") | K7: =IF(K239>=Assumptions!$H$146,"OK","ERROR") | L7: =IF(L239>=Assumptions!$H$146,"OK","ERROR") | M7: =IF(M239>=Assumptions!$H$146,"OK","ERROR") | N7: =IF(N239>=Assumptions!$H$146,"OK","ERROR") | O7: =IF(O239>=Assumptions!$H$146,"OK","ERROR")
I10: Actual | M10: Projected
H11: 2023A | I11: 2024A | J11: 2025A | K11: 2026P | L11: 2027P | M11: 2028P | N11: 2029P | O11: 2030P
C13: LOAN BOOK & IFRS 9 PROVISIONING
H14: =H11 | I14: =I11 | J14: =J11 | K14: =K11 | L14: =L11 | M14: =M11 | N14: =N11 | O14: =O11
C16: Term Loans
C17: Gross — Stage 1 | F17: (KES MM) | H17: 61346.247 | I17: 68190.208 | J17: 74732.268 | K17: =J17-Assumptions!$H$55*J17+Assumptions!$H$56*J18+Assumptions!$H$50*(J17+J18+J19)+Assumptions!$H$59*J19 | L17: =K17-Assumptions!$H$55*K17+Assumptions!$H$56*K18+Assumptions!$H$50*(K17+K18+K19)+Assumptions!$H$59*K19 | M17: =L17-Assumptions!$H$55*L17+Assumptions!$H$56*L18+Assumptions!$H$50*(L17+L18+L19)+Assumptions!$H$59*L19 | N17: =M17-Assumptions!$H$55*M17+Assumptions!$H$56*M18+Assumptions!$H$50*(M17+M18+M19)+Assumptions!$H$59*M19 | O17: =N17-Assumptions!$H$55*N17+Assumptions!$H$56*N18+Assumptions!$H$50*(N17+N18+N19)+Assumptions!$H$59*N19
C18: Gross — Stage 2 | F18: (KES MM) | H18: 3467.725 | I18: 3960.795 | J18: 8355.106 | K18: =J18+Assumptions!$H$55*J17-Assumptions!$H$56*J18-Assumptions!$H$57*J18+Assumptions!$H$58*J19 | L18: =K18+Assumptions!$H$55*K17-Assumptions!$H$56*K18-Assumptions!$H$57*K18+Assumptions!$H$58*K19 | M18: =L18+Assumptions!$H$55*L17-Assumptions!$H$56*L18-Assumptions!$H$57*L18+Assumptions!$H$58*L19 | N18: =M18+Assumptions!$H$55*M17-Assumptions!$H$56*M18-Assumptions!$H$57*M18+Assumptions!$H$58*M19 | O18: =N18+Assumptions!$H$55*N17-Assumptions!$H$56*N18-Assumptions!$H$57*N18+Assumptions!$H$58*N19
C19: Gross — Stage 3 | F19: (KES MM) | H19: 11130.623 | I19: 9335.77 | J19: 12303.29 | K19: =J19+Assumptions!$H$57*J18-Assumptions!$H$58*J19-Assumptions!$H$59*J19 | L19: =K19+Assumptions!$H$57*K18-Assumptions!$H$58*K19-Assumptions!$H$59*K19 | M19: =L19+Assumptions!$H$57*L18-Assumptions!$H$58*L19-Assumptions!$H$59*L19 | N19: =M19+Assumptions!$H$57*M18-Assumptions!$H$58*M19-Assumptions!$H$59*M19 | O19: =N19+Assumptions!$H$57*N18-Assumptions!$H$58*N19-Assumptions!$H$59*N19
C20: Total Gross — Term Loans | H20: =SUM(H17:H19) | I20: =SUM(I17:I19) | J20: =SUM(J17:J19) | K20: =SUM(K17:K19) | L20: =SUM(L17:L19) | M20: =SUM(M17:M19) | N20: =SUM(N17:N19) | O20: =SUM(O17:O19)
C21: ECL — Stage 1 | F21: (KES MM) | H21: 856.406 | I21: 853.147 | J21: 805.781 | K21: =Assumptions!$H$32*Assumptions!$H$75*K17 | L21: =Assumptions!$H$32*Assumptions!$H$75*L17 | M21: =Assumptions!$H$32*Assumptions!$H$75*M17 | N21: =Assumptions!$H$32*Assumptions!$H$75*N17 | O21: =Assumptions!$H$32*Assumptions!$H$75*O17
C22: ECL — Stage 2 | F22: (KES MM) | H22: 337.131 | I22: 429.87 | J22: 672.013 | K22: =Assumptions!$H$38*Assumptions!$H$75*K18 | L22: =Assumptions!$H$38*Assumptions!$H$75*L18 | M22: =Assumptions!$H$38*Assumptions!$H$75*M18 | N22: =Assumptions!$H$38*Assumptions!$H$75*N18 | O22: =Assumptions!$H$38*Assumptions!$H$75*O18
C23: ECL — Stage 3 | F23: (KES MM) | H23: 3807.821 | I23: 4364.636 | J23: 5992.192 | K23: =Assumptions!$H$44*Assumptions!$H$75*K19 | L23: =Assumptions!$H$44*Assumptions!$H$75*L19 | M23: =Assumptions!$H$44*Assumptions!$H$75*M19 | N23: =Assumptions!$H$44*Assumptions!$H$75*N19 | O23: =Assumptions!$H$44*Assumptions!$H$75*O19
C24: Total ECL — Term Loans | H24: =SUM(H21:H23) | I24: =SUM(I21:I23) | J24: =SUM(J21:J23) | K24: =SUM(K21:K23) | L24: =SUM(L21:L23) | M24: =SUM(M21:M23) | N24: =SUM(N21:N23) | O24: =SUM(O21:O23)
C25: Net Loans — Term Loans | F25: (KES MM) | H25: =H20-H24 | I25: =I20-I24 | J25: =J20-J24 | K25: =K20-K24 | L25: =L20-L24 | M25: =M20-M24 | N25: =N20-N24 | O25: =O20-O24
C26: Provision Charge — Term Loans | F26: (KES MM) | I26: =I24-H24 | J26: =J24-I24 | K26: =K24-J24 | L26: =L24-K24 | M26: =M24-L24 | N26: =N24-M24 | O26: =O24-N24
C28: Mortgage
C29: Gross — Stage 1 | F29: (KES MM) | H29: 10183.039 | I29: 11922.527 | J29: 12946.847 | K29: =J29-Assumptions!$I$55*J29+Assumptions!$I$56*J30+Assumptions!$I$50*(J29+J30+J31)+Assumptions!$I$59*J31 | L29: =K29-Assumptions!$I$55*K29+Assumptions!$I$56*K30+Assumptions!$I$50*(K29+K30+K31)+Assumptions!$I$59*K31 | M29: =L29-Assumptions!$I$55*L29+Assumptions!$I$56*L30+Assumptions!$I$50*(L29+L30+L31)+Assumptions!$I$59*L31 | N29: =M29-Assumptions!$I$55*M29+Assumptions!$I$56*M30+Assumptions!$I$50*(M29+M30+M31)+Assumptions!$I$59*M31 | O29: =N29-Assumptions!$I$55*N29+Assumptions!$I$56*N30+Assumptions!$I$50*(N29+N30+N31)+Assumptions!$I$59*N31
C30: Gross — Stage 2 | F30: (KES MM) | H30: 706.859 | I30: 790.821 | J30: 1580.111 | K30: =J30+Assumptions!$I$55*J29-Assumptions!$I$56*J30-Assumptions!$I$57*J30+Assumptions!$I$58*J31 | L30: =K30+Assumptions!$I$55*K29-Assumptions!$I$56*K30-Assumptions!$I$57*K30+Assumptions!$I$58*K31 | M30: =L30+Assumptions!$I$55*L29-Assumptions!$I$56*L30-Assumptions!$I$57*L30+Assumptions!$I$58*L31 | N30: =M30+Assumptions!$I$55*M29-Assumptions!$I$56*M30-Assumptions!$I$57*M30+Assumptions!$I$58*M31 | O30: =N30+Assumptions!$I$55*N29-Assumptions!$I$56*N30-Assumptions!$I$57*N30+Assumptions!$I$58*N31
C31: Gross — Stage 3 | F31: (KES MM) | H31: 2156.329 | I31: 1704.57 | J31: 1395.34 | K31: =J31+Assumptions!$I$57*J30-Assumptions!$I$58*J31-Assumptions!$I$59*J31 | L31: =K31+Assumptions!$I$57*K30-Assumptions!$I$58*K31-Assumptions!$I$59*K31 | M31: =L31+Assumptions!$I$57*L30-Assumptions!$I$58*L31-Assumptions!$I$59*L31 | N31: =M31+Assumptions!$I$57*M30-Assumptions!$I$58*M31-Assumptions!$I$59*M31 | O31: =N31+Assumptions!$I$57*N30-Assumptions!$I$58*N31-Assumptions!$I$59*N31
C32: Total Gross — Mortgage | H32: =SUM(H29:H31) | I32: =SUM(I29:I31) | J32: =SUM(J29:J31) | K32: =SUM(K29:K31) | L32: =SUM(L29:L31) | M32: =SUM(M29:M31) | N32: =SUM(N29:N31) | O32: =SUM(O29:O31)
C33: ECL — Stage 1 | F33: (KES MM) | H33: 14.645 | I33: 29.237 | J33: 13.487 | K33: =Assumptions!$I$32*Assumptions!$H$75*K29 | L33: =Assumptions!$I$32*Assumptions!$H$75*L29 | M33: =Assumptions!$I$32*Assumptions!$H$75*M29 | N33: =Assumptions!$I$32*Assumptions!$H$75*N29 | O33: =Assumptions!$I$32*Assumptions!$H$75*O29
C34: ECL — Stage 2 | F34: (KES MM) | H34: 30.865 | I34: 40.763 | J34: 44.337 | K34: =Assumptions!$I$38*Assumptions!$H$75*K30 | L34: =Assumptions!$I$38*Assumptions!$H$75*L30 | M34: =Assumptions!$I$38*Assumptions!$H$75*M30 | N34: =Assumptions!$I$38*Assumptions!$H$75*N30 | O34: =Assumptions!$I$38*Assumptions!$H$75*O30
C35: ECL — Stage 3 | F35: (KES MM) | H35: 119.874 | I35: 138.613 | J35: 202.602 | K35: =Assumptions!$I$44*Assumptions!$H$75*K31 | L35: =Assumptions!$I$44*Assumptions!$H$75*L31 | M35: =Assumptions!$I$44*Assumptions!$H$75*M31 | N35: =Assumptions!$I$44*Assumptions!$H$75*N31 | O35: =Assumptions!$I$44*Assumptions!$H$75*O31
C36: Total ECL — Mortgage | H36: =SUM(H33:H35) | I36: =SUM(I33:I35) | J36: =SUM(J33:J35) | K36: =SUM(K33:K35) | L36: =SUM(L33:L35) | M36: =SUM(M33:M35) | N36: =SUM(N33:N35) | O36: =SUM(O33:O35)
C37: Net Loans — Mortgage | F37: (KES MM) | H37: =H32-H36 | I37: =I32-I36 | J37: =J32-J36 | K37: =K32-K36 | L37: =L32-L36 | M37: =M32-M36 | N37: =N32-N36 | O37: =O32-O36
C38: Provision Charge — Mortgage | F38: (KES MM) | I38: =I36-H36 | J38: =J36-I36 | K38: =K36-J36 | L38: =L36-K36 | M38: =M36-L36 | N38: =N36-M36 | O38: =O36-N36
C40: Overdraft & Credit Cards
C41: Gross — Stage 1 | F41: (KES MM) | H41: 2053.586 | I41: 2032.539 | J41: 1506.935 | K41: =J41-Assumptions!$J$55*J41+Assumptions!$J$56*J42+Assumptions!$J$50*(J41+J42+J43)+Assumptions!$J$59*J43 | L41: =K41-Assumptions!$J$55*K41+Assumptions!$J$56*K42+Assumptions!$J$50*(K41+K42+K43)+Assumptions!$J$59*K43 | M41: =L41-Assumptions!$J$55*L41+Assumptions!$J$56*L42+Assumptions!$J$50*(L41+L42+L43)+Assumptions!$J$59*L43 | N41: =M41-Assumptions!$J$55*M41+Assumptions!$J$56*M42+Assumptions!$J$50*(M41+M42+M43)+Assumptions!$J$59*M43 | O41: =N41-Assumptions!$J$55*N41+Assumptions!$J$56*N42+Assumptions!$J$50*(N41+N42+N43)+Assumptions!$J$59*N43
C42: Gross — Stage 2 | F42: (KES MM) | H42: 411.914 | I42: 136.036 | J42: 461.631 | K42: =J42+Assumptions!$J$55*J41-Assumptions!$J$56*J42-Assumptions!$J$57*J42+Assumptions!$J$58*J43 | L42: =K42+Assumptions!$J$55*K41-Assumptions!$J$56*K42-Assumptions!$J$57*K42+Assumptions!$J$58*K43 | M42: =L42+Assumptions!$J$55*L41-Assumptions!$J$56*L42-Assumptions!$J$57*L42+Assumptions!$J$58*L43 | N42: =M42+Assumptions!$J$55*M41-Assumptions!$J$56*M42-Assumptions!$J$57*M42+Assumptions!$J$58*M43 | O42: =N42+Assumptions!$J$55*N41-Assumptions!$J$56*N42-Assumptions!$J$57*N42+Assumptions!$J$58*N43
C43: Gross — Stage 3 | F43: (KES MM) | H43: 1122.155 | I43: 1208.13 | J43: 638.333 | K43: =J43+Assumptions!$J$57*J42-Assumptions!$J$58*J43-Assumptions!$J$59*J43 | L43: =K43+Assumptions!$J$57*K42-Assumptions!$J$58*K43-Assumptions!$J$59*K43 | M43: =L43+Assumptions!$J$57*L42-Assumptions!$J$58*L43-Assumptions!$J$59*L43 | N43: =M43+Assumptions!$J$57*M42-Assumptions!$J$58*M43-Assumptions!$J$59*M43 | O43: =N43+Assumptions!$J$57*N42-Assumptions!$J$58*N43-Assumptions!$J$59*N43
C44: Total Gross — Overdraft & Credit Cards | H44: =SUM(H41:H43) | I44: =SUM(I41:I43) | J44: =SUM(J41:J43) | K44: =SUM(K41:K43) | L44: =SUM(L41:L43) | M44: =SUM(M41:M43) | N44: =SUM(N41:N43) | O44: =SUM(O41:O43)
C45: ECL — Stage 1 | F45: (KES MM) | H45: 17.823 | I45: 15.484 | J45: 5.971 | K45: =Assumptions!$J$32*Assumptions!$H$75*K41 | L45: =Assumptions!$J$32*Assumptions!$H$75*L41 | M45: =Assumptions!$J$32*Assumptions!$H$75*M41 | N45: =Assumptions!$J$32*Assumptions!$H$75*N41 | O45: =Assumptions!$J$32*Assumptions!$H$75*O41
C46: ECL — Stage 2 | F46: (KES MM) | H46: 26.92 | I46: 12.963 | J46: 27.542 | K46: =Assumptions!$J$38*Assumptions!$H$75*K42 | L46: =Assumptions!$J$38*Assumptions!$H$75*L42 | M46: =Assumptions!$J$38*Assumptions!$H$75*M42 | N46: =Assumptions!$J$38*Assumptions!$H$75*N42 | O46: =Assumptions!$J$38*Assumptions!$H$75*O42
C47: ECL — Stage 3 | F47: (KES MM) | H47: 445.633 | I47: 488.118 | J47: 257.024 | K47: =Assumptions!$J$44*Assumptions!$H$75*K43 | L47: =Assumptions!$J$44*Assumptions!$H$75*L43 | M47: =Assumptions!$J$44*Assumptions!$H$75*M43 | N47: =Assumptions!$J$44*Assumptions!$H$75*N43 | O47: =Assumptions!$J$44*Assumptions!$H$75*O43
C48: Total ECL — Overdraft & Credit Cards | H48: =SUM(H45:H47) | I48: =SUM(I45:I47) | J48: =SUM(J45:J47) | K48: =SUM(K45:K47) | L48: =SUM(L45:L47) | M48: =SUM(M45:M47) | N48: =SUM(N45:N47) | O48: =SUM(O45:O47)
C49: Net Loans — Overdraft & Credit Cards | F49: (KES MM) | H49: =H44-H48 | I49: =I44-I48 | J49: =J44-J48 | K49: =K44-K48 | L49: =L44-L48 | M49: =M44-M48 | N49: =N44-N48 | O49: =O44-O48
C50: Provision Charge — Overdraft & Credit Cards | F50: (KES MM) | I50: =I48-H48 | J50: =J48-I48 | K50: =K48-J48 | L50: =L48-K48 | M50: =M48-L48 | N50: =N48-M48 | O50: =O48-N48
C52: Off-Balance-Sheet Exposure
C53: Off-Balance-Sheet Balance | F53: (KES MM) | H53: 3718.24 | I53: 3800.743 | J53: 3094.008 | K53: =J53*(1+Assumptions!$H$64) | L53: =K53*(1+Assumptions!$H$64) | M53: =L53*(1+Assumptions!$H$64) | N53: =M53*(1+Assumptions!$H$64) | O53: =N53*(1+Assumptions!$H$64)
C54: Off-Balance-Sheet RWA | F54: (KES MM) | H54: =H53*Assumptions!$H$65*Assumptions!$H$66 | I54: =I53*Assumptions!$H$65*Assumptions!$H$66 | J54: =J53*Assumptions!$H$65*Assumptions!$H$66 | K54: =K53*Assumptions!$H$65*Assumptions!$H$66 | L54: =L53*Assumptions!$H$65*Assumptions!$H$66 | M54: =M53*Assumptions!$H$65*Assumptions!$H$66 | N54: =N53*Assumptions!$H$65*Assumptions!$H$66 | O54: =O53*Assumptions!$H$65*Assumptions!$H$66
C56: Loan Book — Aggregate
C57: Total Gross Loans | H57: =H20+H32+H44 | I57: =I20+I32+I44 | J57: =J20+J32+J44 | K57: =K20+K32+K44 | L57: =L20+L32+L44 | M57: =M20+M32+M44 | N57: =N20+N32+N44 | O57: =O20+O32+O44
C58: Total ECL Allowance | H58: =H24+H36+H48 | I58: =I24+I36+I48 | J58: =J24+J36+J48 | K58: =K24+K36+K48 | L58: =L24+L36+L48 | M58: =M24+M36+M48 | N58: =N24+N36+N48 | O58: =O24+O36+O48
C59: Total Net Loans | H59: =H57-H58 | I59: =I57-I58 | J59: =J57-J58 | K59: =K57-K58 | L59: =L57-L58 | M59: =M57-M58 | N59: =N57-N58 | O59: =O57-O58
C60: Total Stage 3 (NPL) Gross | F60: (KES MM) | H60: =H19+H31+H43 | I60: =I19+I31+I43 | J60: =J19+J31+J43 | K60: =K19+K31+K43 | L60: =L19+L31+L43 | M60: =M19+M31+M43 | N60: =N19+N31+N43 | O60: =O19+O31+O43
C61: NPL Ratio | H61: =IF(H57<>0,H60/H57,0) | I61: =IF(I57<>0,I60/I57,0) | J61: =IF(J57<>0,J60/J57,0) | K61: =IF(K57<>0,K60/K57,0) | L61: =IF(L57<>0,L60/L57,0) | M61: =IF(M57<>0,M60/M57,0) | N61: =IF(N57<>0,N60/N57,0) | O61: =IF(O57<>0,O60/O57,0)
C62: Total Provision Charge | I62: =I26+I38+I50 | J62: =J26+J38+J50 | K62: =K26+K38+K50 | L62: =L26+L38+L50 | M62: =M26+M38+M50 | N62: =N26+N38+N50 | O62: =O26+O38+O50
C64: Loan Book Concentration — Sector Detail (Actuals, disclosed)
C65: Family Bank changed its sector classification scheme between FY2023 (7 categories) and FY2024/FY2025 (10 categories, FY2024 restated into the new scheme in the FY2025 report) — shown as two separate tables rather than forced into one. No CBK sector-concentration limit is disclosed anywhere to check this against.
C67: 10-Category Scheme (2023 not available in this scheme)
H68: =H11 | I68: =I11 | J68: =J11
C69: Agriculture | F69: (KES MM) | I69: 5018.959 | J69: 8162.107
C70: Building & Construction | F70: (KES MM) | I70: 3955.368 | J70: 4966.298
C71: Energy & Water | F71: (KES MM) | I71: 1122.413 | J71: 1260.169
C72: Finance & Insurance Services | F72: (KES MM) | I72: 3292.526 | J72: 3371.756
C73: Manufacturing | F73: (KES MM) | I73: 4463.402 | J73: 5764.765
C74: Personal/Household | F74: (KES MM) | I74: 26080.949 | J74: 30446.85
C75: Real Estate | F75: (KES MM) | I75: 10858.692 | J75: 10577.623
C76: Tourism, Restaurant & Hotels | F76: (KES MM) | I76: 2422.828 | J76: 2683.742
C77: Trade | F77: (KES MM) | I77: 31349.652 | J77: 33914.447
C78: Transport & Communication | F78: (KES MM) | I78: 4343.776 | J78: 4751.155
C79: Total | I79: =I69+I70+I71+I72+I73+I74+I75+I76+I77+I78 | J79: =J69+J70+J71+J72+J73+J74+J75+J76+J77+J78
C80: % of Total — Agriculture | I80: =IF(I79<>0,I69/I79,0) | J80: =IF(J79<>0,J69/J79,0)
C81: % of Total — Building & Construction | I81: =IF(I79<>0,I70/I79,0) | J81: =IF(J79<>0,J70/J79,0)
C82: % of Total — Energy & Water | I82: =IF(I79<>0,I71/I79,0) | J82: =IF(J79<>0,J71/J79,0)
C83: % of Total — Finance & Insurance Services | I83: =IF(I79<>0,I72/I79,0) | J83: =IF(J79<>0,J72/J79,0)
C84: % of Total — Manufacturing | I84: =IF(I79<>0,I73/I79,0) | J84: =IF(J79<>0,J73/J79,0)
C85: % of Total — Personal/Household | I85: =IF(I79<>0,I74/I79,0) | J85: =IF(J79<>0,J74/J79,0)
C86: % of Total — Real Estate | I86: =IF(I79<>0,I75/I79,0) | J86: =IF(J79<>0,J75/J79,0)
C87: % of Total — Tourism, Restaurant & Hotels | I87: =IF(I79<>0,I76/I79,0) | J87: =IF(J79<>0,J76/J79,0)
C88: % of Total — Trade | I88: =IF(I79<>0,I77/I79,0) | J88: =IF(J79<>0,J77/J79,0)
C89: % of Total — Transport & Communication | I89: =IF(I79<>0,I78/I79,0) | J89: =IF(J79<>0,J78/J79,0)
C92: FY2023 — Prior 7-Category Scheme (not directly comparable to above)
C93: Manufacturing | F93: (KES MM) | H93: 1164.055
C94: Wholesale and Retail | F94: (KES MM) | H94: 35411.499
C95: Transport and Communication | F95: (KES MM) | H95: 4623.765
C96: Agriculture | F96: (KES MM) | H96: 5949.684
C97: Business Services | F97: (KES MM) | H97: 3305.282
C98: Building and Construction | F98: (KES MM) | H98: 3777.774
C99: Other | F99: (KES MM) | H99: 32689.3
C100: Total | H100: =H93+H94+H95+H96+H97+H98+H99
C102: SECURITIES, DEPOSITS & NET INTEREST INCOME
H103: =H11 | I103: =I11 | J103: =J11 | K103: =K11 | L103: =L11 | M103: =M11 | N103: =N11 | O103: =O11
C105: Investment Securities
C106: Government Securities Balance | F106: (KES MM) | H106: 34805.638 | I106: 50988.8 | J106: 74014.473 | K106: =J106*(1+Assumptions!$H$91) | L106: =K106*(1+Assumptions!$H$91) | M106: =L106*(1+Assumptions!$H$91) | N106: =M106*(1+Assumptions!$H$91) | O106: =N106*(1+Assumptions!$H$91)
C107: Securities Interest Income | F107: (KES MM) | K107: =K106*Assumptions!$H$92 | L107: =L106*Assumptions!$H$92 | M107: =M106*Assumptions!$H$92 | N107: =N106*Assumptions!$H$92 | O107: =O106*Assumptions!$H$92
C109: Deposits / Funding
C110: Demand / Current — Balance | F110: (KES MM) | H110: =0.300000*103137.731 | I110: =0.300000*127142.024 | J110: =0.300000*152437.336 | K110: =J110*(1+Assumptions!$H$83) | L110: =K110*(1+Assumptions!$H$83) | M110: =L110*(1+Assumptions!$H$83) | N110: =M110*(1+Assumptions!$H$83) | O110: =N110*(1+Assumptions!$H$83)
C111: Demand / Current — Interest Expense | F111: (KES MM) | K111: =K110*Assumptions!$H$87 | L111: =L110*Assumptions!$H$87 | M111: =M110*Assumptions!$H$87 | N111: =N110*Assumptions!$H$87 | O111: =O110*Assumptions!$H$87
C112: Savings — Balance | F112: (KES MM) | H112: =0.250000*103137.731 | I112: =0.250000*127142.024 | J112: =0.250000*152437.336 | K112: =J112*(1+Assumptions!$I$83) | L112: =K112*(1+Assumptions!$I$83) | M112: =L112*(1+Assumptions!$I$83) | N112: =M112*(1+Assumptions!$I$83) | O112: =N112*(1+Assumptions!$I$83)
C113: Savings — Interest Expense | F113: (KES MM) | K113: =K112*Assumptions!$I$87 | L113: =L112*Assumptions!$I$87 | M113: =M112*Assumptions!$I$87 | N113: =N112*Assumptions!$I$87 | O113: =O112*Assumptions!$I$87
C114: Term / Fixed Deposits — Balance | F114: (KES MM) | H114: =0.350000*103137.731 | I114: =0.350000*127142.024 | J114: =0.350000*152437.336 | K114: =J114*(1+Assumptions!$J$83) | L114: =K114*(1+Assumptions!$J$83) | M114: =L114*(1+Assumptions!$J$83) | N114: =M114*(1+Assumptions!$J$83) | O114: =N114*(1+Assumptions!$J$83)
C115: Term / Fixed Deposits — Interest Expense | F115: (KES MM) | K115: =K114*Assumptions!$J$87 | L115: =L114*Assumptions!$J$87 | M115: =M114*Assumptions!$J$87 | N115: =N114*Assumptions!$J$87 | O115: =O114*Assumptions!$J$87
C116: Wholesale / Interbank — Balance | F116: (KES MM) | H116: =0.100000*103137.731 | I116: =0.100000*127142.024 | J116: =0.100000*152437.336 | K116: =J116*(1+Assumptions!$K$83) | L116: =K116*(1+Assumptions!$K$83) | M116: =L116*(1+Assumptions!$K$83) | N116: =M116*(1+Assumptions!$K$83) | O116: =N116*(1+Assumptions!$K$83)
...

Sheet Output
C1: Family Bank Limited | O1: =HYPERLINK("#'Scenarios'!D5","Currently running: "&UPPER(CHOOSE('Scenarios'!$D$5,"Base","Best","Worst"))&" CASE")
C3: Equity Valuation — Base Case
C5: COST OF EQUITY (CAPM)
C6: Risk-free rate | H6: =Assumptions!$H$149
C7: Beta | H7: =Assumptions!$H$151
C8: Equity risk premium | H8: =Assumptions!$H$150
C9: Cost of equity | H9: =Assumptions!$H$153
C11: DIVIDEND DISCOUNT MODEL (multi-stage)
K12: 2026P | L12: 2027P | M12: 2028P | N12: 2029P | O12: 2030P
C13: Dividends | F13: (KES MM) | K13: ='Model'!K141 | L13: ='Model'!L141 | M13: ='Model'!M141 | N13: ='Model'!N141 | O13: ='Model'!O141
C14: PV of Dividends | F14: (KES MM) | K14: =K13/(1+H9)^1 | L14: =L13/(1+H9)^2 | M14: =M13/(1+H9)^3 | N14: =N13/(1+H9)^4 | O14: =O13/(1+H9)^5
C15: Terminal value (Gordon growth) | H15: =O13*(1+Assumptions!$H$152)/(H9-Assumptions!$H$152)
C16: PV of terminal value | H16: =H15/(1+H9)^5
C17: DDM Implied Equity Value | H17: =SUM(K14:O14)+H16
C18: DDM Implied Value Per Share (KES) | H18: =H17/Assumptions!$H$154
C20: RESIDUAL INCOME / EXCESS RETURN MODEL (cross-check)
K21: 2026P | L21: 2027P | M21: 2028P | N21: 2029P | O21: 2030P
C22: Book Equity (period-end) | F22: (KES MM) | K22: ='Model'!K206 | L22: ='Model'!L206 | M22: ='Model'!M206 | N22: ='Model'!N206 | O22: ='Model'!O206
C23: ROE (on opening equity) | K23: =IFERROR('Model'!K140/Assumptions!$H$128,0) | L23: =IFERROR('Model'!L140/K22,0) | M23: =IFERROR('Model'!M140/L22,0) | N23: =IFERROR('Model'!N140/M22,0) | O23: =IFERROR('Model'!O140/N22,0)
C24: Residual Income | F24: (KES MM) | K24: =(K23-H9)*Assumptions!$H$128 | L24: =(L23-H9)*K22 | M24: =(M23-H9)*L22 | N24: =(N23-H9)*M22 | O24: =(O23-H9)*N22
C25: PV of Residual Income | F25: (KES MM) | K25: =K24/(1+H9)^1 | L25: =L24/(1+H9)^2 | M25: =M24/(1+H9)^3 | N25: =N24/(1+H9)^4 | O25: =O24/(1+H9)^5
C26: Terminal residual income value | H26: =O24*(1+Assumptions!$H$152)/(H9-Assumptions!$H$152)
C27: PV of terminal residual income | H27: =H26/(1+H9)^5
C28: Residual Income Implied Equity Value | H28: =Assumptions!$H$128+SUM(K25:O25)+H27
C29: Residual Income Implied Value Per Share (KES) | H29: =H28/Assumptions!$H$154
C31: RELATIVE VALUATION — P/B-ROE REGRESSION
C32: Final-year ROE (on opening equity) | H32: =O23
C33: Implied P/B (regression slope x ROE + intercept) | H33: =Assumptions!$H$174*H32+Assumptions!$H$175
C34: P/B-ROE Regression Implied Equity Value | H34: =H33*'Model'!O206
C35: P/B-ROE Regression Implied Value Per Share (KES) | H35: =H34/Assumptions!$H$154
C37: SUMMARY — IMPLIED EQUITY VALUE BY METHOD
C38: Method | H38: Total (KES MM) | I38: Per Share (KES)
C39: Dividend Discount Model (DDM) | H39: =H17 | I39: =H18
C40: Residual Income / Excess Return | H40: =H28 | I40: =H29
C41: P/B-ROE Regression (relative) | H41: =H34 | I41: =H35
C43: BLENDED VALUATION (weighted: DDM primary / RI cross-check / P-B-ROE market check)
C44: Blended Implied Equity Value | H44: =Assumptions!$H$157*H17+Assumptions!$H$158*H28+Assumptions!$H$159*H34 | J44: Weights are editable on the Assumptions sheet — see BLUEPRINT.md "Blended valuation" for the industry-practice rationale behind this weighting.
C45: Blended Implied Value Per Share (KES) | H45: =H44/Assumptions!$H$154
C47: BOOK VALUE PER SHARE (Actuals, cross-check)
C48: Total Equity ÷ that year's own share count (share count changed year to year via the FY2023 rights issue and FY2025 private placement — not the FY2025 count applied retroactively). Uses our Bank-basis Total Equity, so runs slightly below Family Bank's own disclosed Group-basis BVPS (e.g. FY2025: ours ~19.31 vs the disclosed 19.62) — expected, not an error, per this model's bank-not-group basis.
H50: 2023A | I50: 2024A | J50: 2025A
C51: Book Value Per Share (KES) | H51: =IFERROR('Model'!H206/1287.108,0) | I51: =IFERROR('Model'!I206/1305.195,0) | J51: =IFERROR('Model'!J206/1662.655,0)
C53: FINANCIAL STATEMENT QUALITY ANALYSIS (Actuals only — 2023-2025)
C54: Evaluates the reported actuals for signs of earnings management/manipulation — scoped to the 3 actual years only. The projection is our own modeling, not a filing to scrutinize.
H56: 2023A | I56: 2024A | J56: 2025A
C58: Accruals Ratio (Sloan, 1996) — applies to banks unmodified
C59: (PAT − Operating Cash Flow) / Average Total Assets. A rising ratio means profit is increasingly outpacing the cash actually generated — the classic earnings-quality red flag.
C60: Average Total Assets (2023: period-end — no 2022 figure on record) | F60: (KES MM) | H60: ='Model'!H189 | I60: =('Model'!H189+'Model'!I189)/2 | J60: =('Model'!I189+'Model'!J189)/2
C61: Accruals Ratio | H61: =('Model'!H140-'Model'!H171)/H60 | I61: =('Model'!I140-'Model'!I171)/I60 | J61: =('Model'!J140-'Model'!J171)/J60
C63: Profitability vs. Operating Cash Flow Trend
C64: Net Profit After Tax (PAT) | F64: (KES MM) | H64: ='Model'!H140 | I64: ='Model'!I140 | J64: ='Model'!J140
C65: Operating Cash Flow (OCF) | F65: (KES MM) | H65: ='Model'!H171 | I65: ='Model'!I171 | J65: ='Model'!J171
C66: OCF / PAT | H66: =IFERROR('Model'!H171/'Model'!H140,0) | I66: =IFERROR('Model'!I171/'Model'!I140,0) | J66: =IFERROR('Model'!J171/'Model'!J140,0)
C67: Trend Flag (OCF/PAT vs. prior year) | I67: =IF(I66<H66,"FLAG: declining","OK") | J67: =IF(J66<I66,"FLAG: declining","OK")
C69: Texas Ratio — bank-specific distress indicator (Cassidy, 1980s Texas banking crisis)
C70: Stage 3 Gross NPLs / (Total Equity + Total Loan Loss Reserves). Historically, >100% has been a strong signal of severe bank distress.
C71: Texas Ratio (Total Equity used as Tangible Common Equity proxy — no intangibles disclosed separately) | H71: =IFERROR('Model'!H60/('Model'!H206+'Model'!H58),0) | I71: =IFERROR('Model'!I60/('Model'!I206+'Model'!I58),0) | J71: =IFERROR('Model'!J60/('Model'!J206+'Model'!J58),0)
C73: Beneish M-Score — Adapted Proxy for Financial Institutions
C74: CAVEAT: the standard Beneish M-Score explicitly excludes financial institutions — Sales/Receivables/Gross-Margin/COGS concepts don't translate to a bank balance sheet. Below substitutes bank-equivalent concepts per component and omits the Depreciation Index (no actual-year D&A breakdown disclosed). Interpret directionally only — NOT against the original model's -2.22 threshold.
C75: Every index needs a prior year, so only 2024 and 2025 are computable (2023 has no 2022 comparative on record).
C77: DSRI proxy (Net Loans / Total Op. Income index) | I77: =IFERROR(('Model'!I59/('Model'!I124+'Model'!I129))/('Model'!H59/('Model'!H124+'Model'!H129)),0) | J77: =IFERROR(('Model'!J59/('Model'!J124+'Model'!J129))/('Model'!I59/('Model'!I124+'Model'!I129)),0)
C78: GMI proxy (prior NIM / current NIM) | I78: =IFERROR(('Model'!H124/'Model'!H118)/('Model'!I124/'Model'!I118),0) | J78: =IFERROR(('Model'!I124/'Model'!I118)/('Model'!J124/'Model'!J118),0)
C79: AQI proxy (Other Assets / Total Assets index) | I79: =IFERROR(('Model'!I159/'Model'!I189)/('Model'!H159/'Model'!H189),0) | J79: =IFERROR(('Model'!J159/'Model'!J189)/('Model'!I159/'Model'!I189),0)
C80: SGI (Total Operating Income growth index) | I80: =IFERROR(('Model'!I124+'Model'!I129)/('Model'!H124+'Model'!H129),0) | J80: =IFERROR(('Model'!J124+'Model'!J129)/('Model'!I124+'Model'!I129),0)
C81: SGAI proxy (Cost-to-Income index) | I81: =IFERROR(('Model'!I136/('Model'!I124+'Model'!I129))/('Model'!H136/('Model'!H124+'Model'!H129)),0) | J81: =IFERROR(('Model'!J136/('Model'!J124+'Model'!J129))/('Model'!I136/('Model'!I124+'Model'!I129)),0)
C82: TATA (Total Accruals / Total Assets, point-in-time) | H82: =('Model'!H140-'Model'!H171)/'Model'!H189 | I82: =('Model'!I140-'Model'!I171)/'Model'!I189 | J82: =('Model'!J140-'Model'!J171)/'Model'!J189
C83: LVGI (Leverage Index) | I83: =IFERROR(('Model'!I195/'Model'!I189)/('Model'!H195/'Model'!H189),0) | J83: =IFERROR(('Model'!J195/'Model'!J189)/('Model'!I195/'Model'!I189),0)
C84: Beneish M-Score (adapted proxy, DEPI omitted) | I84: =-4.84+0.92*I77+0.528*I78+0.404*I79+0.892*I80-0.172*I81+4.679*I82-0.327*I83 | J84: =-4.84+0.92*J77+0.528*J78+0.404*J79+0.892*J80-0.172*J81+4.679*J82-0.327*J83

Sheet Sources
C1: FAMILY BANK LIMITED — DATA SOURCES & REFERENCES
C2: Third-party market data used in this model's Output-sheet valuation (CAPM inputs, peer bank P/B multiples). Family Bank's own audited financial-statement figures are cited separately via research_output.md and the Assumptions sheet's data-provenance color legend.
C4: REFERENCES
C5: # | D5: Item / Value | E5: Value | F5: Source | G5: Accessed
C6: [1] | D6: Risk-free rate — Kenya 10-Year Government Bond Yield | E6: 12.32% | F6: =HYPERLINK("https://tradingeconomics.com/kenya/government-bond-yield","Trading Economics") | G6: 2026-07-02
C7: [2] | D7: Equity risk premium — Kenya (total: mature-market ERP + country risk premium) | E7: 13.94% | F7: =HYPERLINK("https://pages.stern.nyu.edu/~adamodar/New_Home_Page/datafile/ctryprem.html","Aswath Damodaran, 'Country Default Spreads and Risk Premiums' (NYU Stern, Jan 2026 data update)") | G7: 2026-07-24
C8: [3] | D8: Beta — average of 6 NSE-listed Kenyan peer bank equity betas (Absa 0.44, Co-op 0.52, DTB 0.28, Equity Group 0.59, I&M 0.80, KCB 0.66) | E8: 0.55 | F8: =HYPERLINK("https://live.mystocks.co.ke/","MyStocks Kenya") | G8: 2026-07-24
C9: [4] | D9: Absa Bank Kenya — Price/Book (BVPS 19.58, share price 33.00) | E9: 1.69x | F9: =HYPERLINK("https://stockanalysis.com/","StockAnalysis.com") | G9: 2026-07-24
C10: [5] | D10: Co-operative Bank of Kenya — Price/Book (BVPS 29.61, share price 35.00) | E10: 1.18x | F10: =HYPERLINK("https://stockanalysis.com/","StockAnalysis.com") | G10: 2026-07-24
C11: [6] | D11: Diamond Trust Bank (DTB, ticker DTK) — Price/Book (BVPS 377.77, share price 150.75) | E11: 0.36x | F11: =HYPERLINK("https://stockanalysis.com/quote/nase/DTK/statistics/","StockAnalysis.com") | G11: 2026-07-24
C12: [7] | D12: Equity Group Holdings — Price/Book (BVPS 86.57, share price 87.00) | E12: 0.96x | F12: =HYPERLINK("https://stockanalysis.com/","StockAnalysis.com") | G12: 2026-07-24
C13: [8] | D13: I&M Group — Price/Book (Book Value Per Share KES 66; share price ~42.50, company chart) | E13: 0.64x | F13: I&M Group FY2025 Integrated Report, p.120 | G13: 2026-07-06
C14: [9] | D14: KCB Group — Price/Book (BVPS 109.61, share price 82.50) | E14: 0.73x | F14: =HYPERLINK("https://stockanalysis.com/","StockAnalysis.com") | G14: 2026-07-24
C15: [10] | D15: NCBA Group — Price/Book (directly disclosed) | E15: 1.2x | F15: NCBA Group Plc FY2025 Annual Integrated Report, p.32 | G15: 2026-07-06
C16: [11] | D16: Stanbic Holdings — Price/Book (BVPS 202.74, share price 292.00) | E16: 1.44x | F16: =HYPERLINK("https://stockanalysis.com/","StockAnalysis.com") | G16: 2026-07-24
C17: [12] | D17: Standard Chartered Bank Kenya (ticker SCBK) — Price/Book (BVPS 184.79, share price 334.25) | E17: 1.81x | F17: =HYPERLINK("https://stockanalysis.com/quote/nase/SCBK/statistics/","StockAnalysis.com") | G17: 2026-07-24
C19: Convention: Item/Value cited, Source (publisher — hyperlinked where a URL is available), Accessed (date the figure was pulled). Matches standard equity-research citation practice — see research_output.md for the full research log behind each entry.
